urbani/__init__.py
urbani/config.py
urbani/urbani.py
urbani-0.1.4.dist-info/METADATA
urbani-0.1.4.dist-info/WHEEL
urbani-0.1.4.dist-info/top_level.txt
urbani-0.1.4.dist-info/RECORD
