Metadata-Version: 2.1
Name: urbani
Version: 0.1.4
Summary: URBAN-i API client library
Home-page: https://github.com/urbanist-ai/urbani_api
Author: Mohamed Ibrahim
Author-email: contact@urban-i.ai
Classifier: Programming Language :: Python :: 3
Classifier: License :: Other/Proprietary License
Classifier: Operating System :: OS Independent
Requires-Python: >=3.6
Requires-Dist: requests
